{
  "Modifiers": [
    {
      "Zones": [
        {
          "Name": "Car Track",
          "TopLeft": "X=290411.125 Y=-734055.500",
          "BottomRight": "X=241022.234 Y=-773566.625"
        }
      ],
      "SpawnerProbabilityMultiplier": 1,
      "SpawnerQuantityMultiplier": 2,
      "ExamineSpawnerProbabilityMultiplier": 1,
      "ExamineSpawnerQuantityMultiplier": 2
    },
    {
      "Zones": [
        {
          "Name": "Mine",
          "TopLeft": "X=-774977.812 Y=-710066.688",
          "BottomRight": "X=-477233.344 Y=407533.344"
        }
      ],
      "SpawnerProbabilityMultiplier": 1,
      "SpawnerQuantityMultiplier": 2,
      "ExamineSpawnerProbabilityMultiplier": 1,
      "ExamineSpawnerQuantityMultiplier": 2
    }
  ]
}